solidlab_perftest_agent/api_calls.py
solidlab_perftest_agent/config.py
solidlab_perftest_agent/main.py
solidlab_perftest_agent-1.0.0.dist-info/LICENSE
solidlab_perftest_agent-1.0.0.dist-info/METADATA
solidlab_perftest_agent-1.0.0.dist-info/WHEEL
solidlab_perftest_agent-1.0.0.dist-info/entry_points.txt
solidlab_perftest_agent-1.0.0.dist-info/top_level.txt
solidlab_perftest_agent-1.0.0.dist-info/RECORD
