Metadata-Version: 2.1
Name: solidlab-perftest-agent
Version: 1.0.0
Summary: SolidLab PerfTest Agent
Home-page: https://github.com/SolidLabResearch/solidlab-perftest-agent
Author: Wim Van de Meerssche
Author-email: wim.vandemeerssche@imec.be
License: EUPL-1.2
Classifier: Development Status :: 4 - Beta
Classifier: Environment :: Console
Classifier: License :: OSI Approved :: European Union Public Licence 1.2 (EUPL 1.2)
Classifier: Programming Language :: Python :: 3 :: Only
Requires-Python: >=3.7
License-File: LICENSE
Requires-Dist: python-dateutil
Requires-Dist: requests
Requires-Dist: solidlab-perftest-common <5,>=4.0.2
Requires-Dist: aiofiles
Requires-Dist: aiohttp[speedups]
